LICENSE
MANIFEST.in
README.md
config.py
setup.cfg
setup.py
fab_addon_geoalchemy/__init__.py
fab_addon_geoalchemy/fields.py
fab_addon_geoalchemy/manager.py
fab_addon_geoalchemy/models.py
fab_addon_geoalchemy/version.py
fab_addon_geoalchemy/views.py
fab_addon_geoalchemy/widgets.py
fab_addon_geoalchemy.egg-info/PKG-INFO
fab_addon_geoalchemy.egg-info/SOURCES.txt
fab_addon_geoalchemy.egg-info/dependency_links.txt
fab_addon_geoalchemy.egg-info/not-zip-safe
fab_addon_geoalchemy.egg-info/requires.txt
fab_addon_geoalchemy.egg-info/top_level.txt
fab_addon_geoalchemy/static/fab_addon_geoalchemy/css/leaflet.css
fab_addon_geoalchemy/static/fab_addon_geoalchemy/css/map.css
fab_addon_geoalchemy/static/fab_addon_geoalchemy/js/leaflet.js
fab_addon_geoalchemy/static/fab_addon_geoalchemy/js/main.js
fab_addon_geoalchemy/templates/404.html
fab_addon_geoalchemy/templates/latlon_widget.html
fab_addon_geoalchemy/translations/pt/LC_MESSAGES/messages.mo
fab_addon_geoalchemy/translations/pt/LC_MESSAGES/messages.po
test/__init__.py
test/test_fields.py