Metadata-Version: 2.1
Name: fab-addon-geoalchemy
Version: 0.4.1
Summary: Add support for GeoAlchemy2 Geometry fields to Flask Appbuilder
Home-page: https://github.com/dolfandringa/fab_addon_geoalchemy/
Author: Dolf Andringa
Author-email: dolfandringa@gmail.com
License: MIT
Platform: any
Classifier: Development Status :: 5 - Production/Stable
Classifier: Environment :: Web Environment
Classifier: Intended Audience :: Developers
Classifier: License :: OSI Approved :: BSD License
Classifier: Operating System :: OS Independent
Classifier: Programming Language :: Python
Classifier: Topic :: Software Development :: Libraries :: Python Modules
